iexdata/__init__.py
iexdata/common.py
iexdata/stream.py
iexdata/version.py
iexdata/endpoints/__init__.py
iexdata/endpoints/marketdata.py
iexdata/endpoints/markets.py
iexdata/endpoints/refdata.py
iexdata/endpoints/stats.py
iex_data-0.1.0.dist-info/LICENSE
iex_data-0.1.0.dist-info/METADATA
iex_data-0.1.0.dist-info/WHEEL
iex_data-0.1.0.dist-info/top_level.txt
iex_data-0.1.0.dist-info/RECORD
